{
  "tasks": [
    {
      "id": 1,
      "due": "01/01/2021 16:21",
      "assigned": "Manuel Povinho",
      "description": "Fazer TPC de DAW",
      "status": false
    },
    {
      "id": 2,
      "due": "01/01/2021 16:21",
      "assigned": "Manuel Povinho",
      "description": "Fazer TPC de DAW",
      "status": true
    },
    {
      "id": 3,
      "due": "21/11/2024 16:21",
      "assigned": "Manuel Povinho José",
      "description": "Nãoaaaaaaaweaewaewqwqwaqwawqawaewaewaeaewaewaewawaaaaaaaaaaaaaaaaaaaaaaaaaaaaaaaaaaaaaaaaaaaaaaaaaaaaaaaaaa fazer TPC de DAWaaaaaaaaaaaaaaaaaaaaaaaaaaaaaaaaaaaaaaaaaaaaaaaa",
      "status": true
    },
    {
      "id": "597",
      "due": "2020-11-19T23:50",
      "assigned": "Pifea",
      "description": "Pêfego",
      "status": false
    },
    {
      "id": "51447",
      "due": "2020-11-19T23:50",
      "assigned": "Pifea",
      "description": "Pêfego",
      "status": false
    },
    {
      "id": "aaaaa2",
      "due": "2020-11-19T23:54",
      "assigned": "Pifea",
      "description": "Pêfego",
      "status": false
    },
    {
      "id": "5qa",
      "due": "2020-11-19T23:55",
      "assigned": "Pifea",
      "description": "Pêfego",
      "status": false
    },
    {
      "id": "aaaaww",
      "due": "2020-12-11T23:58",
      "assigned": "222",
      "description": "aaaa",
      "status": false
    },
    {
      "id": "5599",
      "due": "2020-11-20T06:00",
      "assigned": "Pifea",
      "description": "aaaa",
      "status": false
    }
  ]
}